taki/__init__.py
taki/taki.py
taki-1.0.dist-info/METADATA
taki-1.0.dist-info/RECORD
taki-1.0.dist-info/WHEEL
taki-1.0.dist-info/entry_points.txt
taki-1.0.dist-info/top_level.txt
