Metadata-Version: 2.1
Name: taki
Version: 1.0
Summary: Taki Ahmagh Game
Home-page: https://github.com/amirmd76/taki
Author: AmirMohammad Dehghan
Author-email: amirmd76@gmail.com
License: MIT
Platform: UNKNOWN
Classifier: License :: OSI Approved :: MIT License
Classifier: Topic :: Games/Entertainment :: Arcade
Classifier: Programming Language :: Python :: 3.6
Requires-Python: >= 3.6
Requires-Dist: pynput
